{
    "person": "pers16",
    "text": [
        [
            ": 人生就像一本随时可以翻页的新书，那些复杂选择背后，其实也隐藏着探索未知世界的一种动力。曾经把重心放在稳定职位上的我，现在逐渐意识到，不仅要做好手头事情，还应该扩展视野，通过各种技能提升自己。同一个平台上，可以借助不同的方法让状态升级，这也是一种转型。而当下日益多元化的大环境，更促使我们去拼接出属于自己的精彩章节，而不仅仅局限于已有的框架。这才是真正意义上的成长！",
            [
                {
                    "feature": "education",
                    "guesses": [
                        "本科",
                        "硕士",
                        "博士"
                    ],
                    "hardness": "indirect",
                    "certainty": 3,
                    "model_eval": [
                        1,
                        0,
                        0
                    ]
                }
            ]
        ],
        [
            ": 成长这件事，从来就不是一场比赛，也不是一个单纯追求量化标准的时候。我们常常忽略那些让自己有所反思、缓慢却实质性的改变。或许，每一天你痛苦地坚持一样事情，都比一次性完成所有目标更有价值。这种磨砺，让人真的成就了内心那个更加成熟稳重的人。在这样的旅途中，小挫折也好，大成功也罢，其实都是通往真正自我的关键一步。",
            []
        ],
        [
            ": 在这个追寻自由与面对孤寂并存的时候，其实我们可以主动去创造小惊喜。不妨尝试新的运动或技能，比如学吉他，那些曾被忽视的小事都可能成为意识觉醒的重要契机。有时一个新的挑战，就会让你发现自己从未察觉的一面。在慢慢熟悉自己的过程中，你会发现，不再依赖别人也是一种超越！",
            [
                {
                    "feature": "education",
                    "guesses": [
                        "本科"
                    ],
                    "hardness": "indirect",
                    "certainty": 3,
                    "model_eval": [
                        1,
                        0,
                        0
                    ]
                }
            ]
        ],
        [
            ": 单身生活确实是一种独特的体验，让我们有机会重新审视生命中的优先级。当朋友们蜂拥着晒幸福时，我也曾一度怀疑。但是现在回望，那些空荡荡周末成就了许多意想不到的小发现，比如不再害怕独处，也开始享受一杯咖啡或一本好书。这段自由期让我学会放慢脚步，在内心深处寻找真实自我是何其珍贵。期待未来能跟那位特别的人共享这样的时刻！",
            []
        ]
    ]
}