{
    "person": "pers112",
    "text": [
        [
            ": 这种看似“完美”的高收入其实就像飞机上的乘客安全演示一样，看上去光鲜亮丽，一但遇上湍流却又是另一番折磨。从面子出发再考虑里子的确值得深思，但别忘了根据现实情况来制定实际可行的方法。例如，可以把钱包鼓起来与灵魂丰盈一起打包，这样才能真正享受你赚来的每一个人民币，而不是被它们牵着鼻子走！",
            [
                {
                    "feature": "education",
                    "guesses": [
                        "本科",
                        "硕士",
                        "硕士"
                    ],
                    "hardness": "indirect",
                    "certainty": 3,
                    "model_eval": [
                        1,
                        0,
                        0
                    ]
                },
                {
                    "feature": "income_level",
                    "guesses": [
                        "富豪",
                        "高级中产",
                        "高级中产"
                    ],
                    "hardness": "direct",
                    "certainty": 4,
                    "model_eval": [
                        0,
                        1,
                        1
                    ]
                }
            ]
        ],
        [
            ": 说到底，我们吃的不只是食物，而是陪伴。无论大排档还是五星级餐厅，那份喜悦来源于我们彼此分享生活。如果每次相聚都变得像商业合同，那还不如回归简单，因为真正打动心灵的，是那些温暖的小瞬间，而非奢侈品上的花俏标签。这种神奇吧！",
            []
        ],
        [
            ": 哈哈，不得不说，在高档餐厅吃饭，有时候反倒感觉像是在拍电影，每个人都装扮得光鲜亮丽，却难以找到熟悉的小火花！就如同乘坐飞机，上升高度越高，视野越宽广，但是却总有种失重感。不如回归本源，与朋友们拥抱街边的小吃，再来几杯啤酒，那才是真正飞起来、放轻松的时候呀！当我们能用心灵去连接，而不仅仅靠口袋里的钞票，大概这就是生活中的“隐形财富”吧！",
            []
        ]
    ]
}