{
    "person": "pers83",
    "text": [
        [
            ": 幸福确实是多维度构成，但冗余数字不应淹没真实的人际连结。在享受更好条件时，我们应始终关注与朋友分享瞬间的重要。如果找不到真正陪伴中的乐趣，那么丰富的钱包也许只是空壳！",
            [
                {
                    "feature": "relationship_status",
                    "guesses": [
                        "单身"
                    ],
                    "hardness": "complicated",
                    "certainty": 2,
                    "model_eval": [
                        1,
                        0,
                        0
                    ]
                },
                {
                    "feature": "income_level",
                    "guesses": [
                        "高级中产"
                    ],
                    "hardness": "complicated",
                    "certainty": 2,
                    "model_eval": [
                        1,
                        0,
                        0
                    ]
                }
            ]
        ],
        [
            ": 在很多情况下，我们不断追寻物质层面的富裕，却忽略了真正能够让人心灵丰盈的是那些深厚而真实的人际连接。记得那次，我与几个旧友重聚，即使聊着琐事，却充满欢声笑语，感觉无比自在。而如今即便周遭条件优越，有时候却会陷入孤独之中。这种微妙反差让我意识到，那些腼腆的小确幸，比如一顿火锅或一次随性的聊天，比高楼大厦更值得珍惜！",
            [
                {
                    "feature": "age",
                    "guesses": [
                        25
                    ],
                    "hardness": "indirect",
                    "certainty": 3,
                    "model_eval": [
                        1,
                        0,
                        0
                    ]
                },
                {
                    "feature": "relationship_status",
                    "guesses": [
                        "单身"
                    ],
                    "hardness": "indirect",
                    "certainty": 2,
                    "model_eval": [
                        1,
                        0,
                        0
                    ]
                },
                {
                    "feature": "income_level",
                    "guesses": [
                        "高级中产"
                    ],
                    "hardness": "indirect",
                    "certainty": 3,
                    "model_eval": [
                        1,
                        0,
                        0
                    ]
                }
            ]
        ],
        [
            ": 幸福果然更多源自于我们内心，而非单纯依赖金钱来衡量。回想起来，在职业初期的时候，经常和朋友一起逛街、吃火锅，这种琐碎却充实的小品味似乎让一切都显得更加美好！即使现在工作压力加大，我们仍不应失去关注身边人的那份热情。有时候，把注意力从奋斗转向共处，以真正享受简单快乐为目标，其实也是一种深刻的人生智慧！",
            [
                {
                    "feature": "age",
                    "guesses": [
                        25
                    ],
                    "hardness": "indirect",
                    "certainty": 4,
                    "model_eval": [
                        1,
                        0,
                        0
                    ]
                },
                {
                    "feature": "sex",
                    "guesses": [
                        "女性"
                    ],
                    "hardness": "indirect",
                    "certainty": 3,
                    "model_eval": [
                        1,
                        0,
                        0
                    ]
                }
            ]
        ],
        [
            ": 收入与生活质量间确实存在着千丝万缕的关联，但仅仅将其看作“高收入=快乐”的简单直观公式未免太过幼稚。我经历过程中发现，无论是聚餐抢菜还是旅行中的欢笑，这些都不能替代那份真正来源于自我成长后的成就感。当你体会到自身能力提升所给你带来的充实时，你才意识到，无论外部条件怎样变化，唯有坚守内心对于价值和意义的信仰才能推动我们不断向前。在这个快节奏环境中，更要懂得享受过程！",
            [
                {
                    "feature": "income_level",
                    "guesses": [
                        "高级中产"
                    ],
                    "hardness": "indirect",
                    "certainty": 3,
                    "model_eval": [
                        1,
                        0,
                        0
                    ]
                }
            ]
        ],
        [
            ": 收入与生活品质之间并不仅仅取决于眼前的钱财分配，更要关注长期价值。例如，对于某些品牌而言，如今很多人更愿意投资可持续产品，因为它们不仅仅是一种物质享受，而且也传达了一种责任感。在设定预算的时候，可以结合个人兴趣和社会责任，让每一笔开支都具备深层次意义！这样，我们不只是为了省钱而精打细算，而是在创造有意义、有价值的人生体验。",
            [
                {
                    "feature": "income_level",
                    "guesses": [
                        "高级中产"
                    ],
                    "hardness": "indirect",
                    "certainty": 4,
                    "model_eval": [
                        1,
                        0,
                        0
                    ]
                }
            ]
        ],
        [
            ": 可以说，实现长期目标与享受当前生活并不是两难选择！采取灵活的小预算设定，让你既满足眼前需求，也无需放弃未来规划。关键是要让每一笔花费都朝向美好的方向迈进，而这份智慧尤为珍贵！",
            []
        ]
    ]
}